{
    "artists": [
        {
            "id": 14594,
            "name": "Pok\u00e9rus Project",
            "url": "https://ocremix.org/artist/14594/pokerus-project"
        }
    ],
    "primary_game": "Pok\u00e9mon Gold Version",
    "tags": [
        {
            "id": "acoustic-guitar",
            "path": "Instrumentation > Acoustic Guitar",
            "url": "https://ocremix.org/tag/acoustic-guitar"
        },
        {
            "id": "electric-guitar",
            "path": "Instrumentation > Electric Guitar",
            "url": "https://ocremix.org/tag/electric-guitar"
        },
        {
            "id": "singing",
            "path": "Instrumentation > Singing",
            "url": "https://ocremix.org/tag/singing"
        },
        {
            "id": "timesig-4-4",
            "path": "Time > 4/4 Time Signature",
            "url": "https://ocremix.org/tag/timesig-4-4"
        },
        {
            "id": "vocals-male",
            "path": "Instrumentation > Vocals: Male",
            "url": "https://ocremix.org/tag/vocals-male"
        }
    ],
    "title": "New Horizons",
    "url": "https://ocremix.org/remix/OCR03270"
}