{
    "artists": [
        {
            "id": 10136,
            "name": "Archangel",
            "url": "https://ocremix.org/artist/10136/archangel"
        }
    ],
    "primary_game": "Final Fantasy VI",
    "tags": [
        {
            "id": "chromatic-percussion",
            "path": "Instrumentation > Chromatic Percussion",
            "url": "https://ocremix.org/tag/chromatic-percussion"
        },
        {
            "id": "cinematic",
            "path": "Genre > Cinematic",
            "url": "https://ocremix.org/tag/cinematic"
        },
        {
            "id": "orchestral",
            "path": "Instrumentation > Orchestral",
            "url": "https://ocremix.org/tag/orchestral"
        },
        {
            "id": "quirky",
            "path": "Mood > Quirky",
            "url": "https://ocremix.org/tag/quirky"
        }
    ],
    "title": "Umaro's New Groove",
    "url": "https://ocremix.org/remix/OCR03055"
}