{
    "artists": [
        {
            "id": 16939,
            "name": "Kade Kalka",
            "url": "https://ocremix.org/artist/16939/kade-kalka"
        }
    ],
    "primary_game": "Xenoblade Chronicles",
    "tags": [
        {
            "id": "dark",
            "path": "Mood > Dark",
            "url": "https://ocremix.org/tag/dark"
        },
        {
            "id": "electric-guitar",
            "path": "Instrumentation > Electric Guitar",
            "url": "https://ocremix.org/tag/electric-guitar"
        },
        {
            "id": "epic",
            "path": "Mood > Epic",
            "url": "https://ocremix.org/tag/epic"
        },
        {
            "id": "live-instruments",
            "path": "Production > Live Instruments",
            "url": "https://ocremix.org/tag/live-instruments"
        },
        {
            "id": "mellow",
            "path": "Mood > Mellow",
            "url": "https://ocremix.org/tag/mellow"
        },
        {
            "id": "metal",
            "path": "Genre > Rock > Metal",
            "url": "https://ocremix.org/tag/metal"
        },
        {
            "id": "prog-rock",
            "path": "Genre > Rock > Progressive Rock",
            "url": "https://ocremix.org/tag/prog-rock"
        },
        {
            "id": "rock",
            "path": "Genre > Rock",
            "url": "https://ocremix.org/tag/rock"
        }
    ],
    "title": "The Shimmering Ether of Satorl",
    "url": "https://ocremix.org/remix/OCR04111",
    "youtube_url": "https://www.youtube.com/watch?v=5jbCPpCaA_o"
}