{
    "artists": [
        {
            "id": 5406,
            "name": "Josh Whelchel",
            "url": "https://ocremix.org/artist/5406/josh-whelchel"
        },
        {
            "id": 10773,
            "name": "Danielle Messina",
            "url": "https://ocremix.org/artist/10773/danielle-messina"
        },
        {
            "id": 10774,
            "name": "Ryan C. Connelly",
            "url": "https://ocremix.org/artist/10774/ryan-c-connelly"
        }
    ],
    "primary_game": "NiGHTS into dreams...",
    "tags": [
        {
            "id": "brass",
            "path": "Instrumentation > Brass",
            "url": "https://ocremix.org/tag/brass"
        },
        {
            "id": "classical",
            "path": "Genre > Classical",
            "url": "https://ocremix.org/tag/classical"
        },
        {
            "id": "collab",
            "path": "Origin > Collaboration",
            "url": "https://ocremix.org/tag/collab"
        },
        {
            "id": "dark",
            "path": "Mood > Dark",
            "url": "https://ocremix.org/tag/dark"
        },
        {
            "id": "duration-long",
            "path": "Time > Duration: Long",
            "url": "https://ocremix.org/tag/duration-long"
        },
        {
            "id": "lyrics-existing",
            "path": "Lyrics > Lyrics: Existing",
            "url": "https://ocremix.org/tag/lyrics-existing"
        },
        {
            "id": "lyrics-original",
            "path": "Lyrics > Lyrics: Original",
            "url": "https://ocremix.org/tag/lyrics-original"
        },
        {
            "id": "opera",
            "path": "Genre > Classical > Opera",
            "url": "https://ocremix.org/tag/opera"
        },
        {
            "id": "singing",
            "path": "Instrumentation > Singing",
            "url": "https://ocremix.org/tag/singing"
        },
        {
            "id": "strings",
            "path": "Instrumentation > Strings",
            "url": "https://ocremix.org/tag/strings"
        },
        {
            "id": "synth",
            "path": "Instrumentation > Synth",
            "url": "https://ocremix.org/tag/synth"
        },
        {
            "id": "vocals-female",
            "path": "Instrumentation > Vocals: Female",
            "url": "https://ocremix.org/tag/vocals-female"
        },
        {
            "id": "vocals-male",
            "path": "Instrumentation > Vocals: Male",
            "url": "https://ocremix.org/tag/vocals-male"
        },
        {
            "id": "world",
            "path": "Regional > World",
            "url": "https://ocremix.org/tag/world"
        }
    ],
    "title": "Dies, Nox et Omnia",
    "url": "https://ocremix.org/remix/OCR02263",
    "youtube_url": "https://www.youtube.com/watch?v=lk6L2ZPVx60"
}