{
    "artists": [
        {
            "id": 5187,
            "name": "The Dual Dragons",
            "url": "https://ocremix.org/artist/5187/the-dual-dragons"
        }
    ],
    "primary_game": "Final Fantasy VIII",
    "tags": [
        {
            "id": "electric-guitar",
            "path": "Instrumentation > Electric Guitar",
            "url": "https://ocremix.org/tag/electric-guitar"
        },
        {
            "id": "rock",
            "path": "Genre > Rock",
            "url": "https://ocremix.org/tag/rock"
        },
        {
            "id": "strings",
            "path": "Instrumentation > Strings",
            "url": "https://ocremix.org/tag/strings"
        },
        {
            "id": "synth",
            "path": "Instrumentation > Synth",
            "url": "https://ocremix.org/tag/synth"
        }
    ],
    "title": "SeeD Mission",
    "url": "https://ocremix.org/remix/OCR01948",
    "youtube_url": "https://www.youtube.com/watch?v=3vtA6s3B9R4"
}