{
    "artists": [
        {
            "id": 10656,
            "name": "Wild_Cat",
            "url": "https://ocremix.org/artist/10656/wild-cat"
        },
        {
            "id": 12064,
            "name": "XPRTNovice",
            "url": "https://ocremix.org/artist/12064/xprtnovice"
        },
        {
            "id": 13045,
            "name": "Ivan Hak\u0161tok",
            "url": "https://ocremix.org/artist/13045/ivan-hakstok"
        },
        {
            "id": 13500,
            "name": "jnWake",
            "url": "https://ocremix.org/artist/13500/jnwake"
        }
    ],
    "primary_game": "Super Final Match Tennis",
    "tags": [
        {
            "id": "choir",
            "path": "Instrumentation > Choir",
            "url": "https://ocremix.org/tag/choir"
        },
        {
            "id": "chromatic-percussion",
            "path": "Instrumentation > Chromatic Percussion",
            "url": "https://ocremix.org/tag/chromatic-percussion"
        },
        {
            "id": "collab",
            "path": "Origin > Collaboration",
            "url": "https://ocremix.org/tag/collab"
        },
        {
            "id": "compo-dod",
            "path": "Origin > Competition > Dwelling of Duels",
            "url": "https://ocremix.org/tag/compo-dod"
        },
        {
            "id": "electric-guitar",
            "path": "Instrumentation > Electric Guitar",
            "url": "https://ocremix.org/tag/electric-guitar"
        },
        {
            "id": "energetic",
            "path": "Mood > Energetic",
            "url": "https://ocremix.org/tag/energetic"
        },
        {
            "id": "organ",
            "path": "Instrumentation > Organ",
            "url": "https://ocremix.org/tag/organ"
        },
        {
            "id": "piano",
            "path": "Instrumentation > Piano",
            "url": "https://ocremix.org/tag/piano"
        },
        {
            "id": "rock",
            "path": "Genre > Rock",
            "url": "https://ocremix.org/tag/rock"
        },
        {
            "id": "saxophone",
            "path": "Instrumentation > Saxophone",
            "url": "https://ocremix.org/tag/saxophone"
        },
        {
            "id": "synth",
            "path": "Instrumentation > Synth",
            "url": "https://ocremix.org/tag/synth"
        },
        {
            "id": "timesig-4-4",
            "path": "Time > 4/4 Time Signature",
            "url": "https://ocremix.org/tag/timesig-4-4"
        }
    ],
    "title": "5 Minutes of Glory",
    "url": "https://ocremix.org/remix/OCR03089"
}