{
    "artists": [
        {
            "id": 13849,
            "name": "Nostalvania",
            "url": "https://ocremix.org/artist/13849/nostalvania"
        },
        {
            "id": 14337,
            "name": "The OC Jazz Collective",
            "url": "https://ocremix.org/artist/14337/the-oc-jazz-collective"
        }
    ],
    "primary_game": "Chrono Trigger",
    "tags": [
        {
            "id": "chill",
            "path": "Mood > Chill",
            "url": "https://ocremix.org/tag/chill"
        },
        {
            "id": "energetic",
            "path": "Mood > Energetic",
            "url": "https://ocremix.org/tag/energetic"
        },
        {
            "id": "extended-soloing",
            "path": "Arrangement > Extended Soloing",
            "url": "https://ocremix.org/tag/extended-soloing"
        },
        {
            "id": "jazz",
            "path": "Genre > Jazz",
            "url": "https://ocremix.org/tag/jazz"
        },
        {
            "id": "jazzy",
            "path": "Mood > Jazzy",
            "url": "https://ocremix.org/tag/jazzy"
        },
        {
            "id": "live-instruments",
            "path": "Production > Live Instruments",
            "url": "https://ocremix.org/tag/live-instruments"
        },
        {
            "id": "piano",
            "path": "Instrumentation > Piano",
            "url": "https://ocremix.org/tag/piano"
        },
        {
            "id": "saxophone",
            "path": "Instrumentation > Saxophone",
            "url": "https://ocremix.org/tag/saxophone"
        },
        {
            "id": "timesig-variable",
            "path": "Time > Time Signature: Variable",
            "url": "https://ocremix.org/tag/timesig-variable"
        }
    ],
    "title": "Time's Seal",
    "url": "https://ocremix.org/remix/OCR03520",
    "youtube_url": "https://www.youtube.com/watch?v=vAj5Ge9slWs"
}