{
    "artists": [
        {
            "id": 4351,
            "name": "Chikusho Sound Team",
            "url": "https://ocremix.org/artist/4351/chikusho-sound-team"
        }
    ],
    "primary_game": "Mega Man X",
    "tags": [
        {
            "id": "acoustic-guitar",
            "path": "Instrumentation > Acoustic Guitar",
            "url": "https://ocremix.org/tag/acoustic-guitar"
        },
        {
            "id": "rock",
            "path": "Genre > Rock",
            "url": "https://ocremix.org/tag/rock"
        },
        {
            "id": "synth",
            "path": "Instrumentation > Synth",
            "url": "https://ocremix.org/tag/synth"
        }
    ],
    "title": "Airbased",
    "url": "https://ocremix.org/remix/OCR00525",
    "youtube_url": "https://www.youtube.com/watch?v=VpBngws8K2k"
}