{
    "artists": [
        {
            "id": 4961,
            "name": "Goomin Nam",
            "url": "https://ocremix.org/artist/4961/goomin-nam"
        }
    ],
    "primary_game": "Final Fantasy VIII",
    "tags": [
        {
            "id": "acoustic-guitar",
            "path": "Instrumentation > Acoustic Guitar",
            "url": "https://ocremix.org/tag/acoustic-guitar"
        },
        {
            "id": "chromatic-percussion",
            "path": "Instrumentation > Chromatic Percussion",
            "url": "https://ocremix.org/tag/chromatic-percussion"
        },
        {
            "id": "easy-listening",
            "path": "Genre > Easy Listening",
            "url": "https://ocremix.org/tag/easy-listening"
        },
        {
            "id": "electric-piano",
            "path": "Instrumentation > Electric Piano",
            "url": "https://ocremix.org/tag/electric-piano"
        },
        {
            "id": "mellow",
            "path": "Mood > Mellow",
            "url": "https://ocremix.org/tag/mellow"
        },
        {
            "id": "strings",
            "path": "Instrumentation > Strings",
            "url": "https://ocremix.org/tag/strings"
        },
        {
            "id": "winter-holiday",
            "path": "Usage > Winter Holiday",
            "url": "https://ocremix.org/tag/winter-holiday"
        },
        {
            "id": "woodwinds",
            "path": "Instrumentation > Woodwinds",
            "url": "https://ocremix.org/tag/woodwinds"
        }
    ],
    "title": "Fisherman's Horizon (Christmas Ver.)",
    "url": "https://ocremix.org/remix/OCR03052",
    "youtube_url": "https://www.youtube.com/watch?v=BTo0TeGVwv8"
}