{
    "artists": [
        {
            "id": 4703,
            "name": "RoeTaKa",
            "url": "https://ocremix.org/artist/4703/roetaka"
        }
    ],
    "primary_game": "Dark Souls",
    "tags": [
        {
            "id": "choir",
            "path": "Instrumentation > Choir",
            "url": "https://ocremix.org/tag/choir"
        },
        {
            "id": "cinematic",
            "path": "Genre > Cinematic",
            "url": "https://ocremix.org/tag/cinematic"
        },
        {
            "id": "classical",
            "path": "Genre > Classical",
            "url": "https://ocremix.org/tag/classical"
        },
        {
            "id": "dark",
            "path": "Mood > Dark",
            "url": "https://ocremix.org/tag/dark"
        },
        {
            "id": "piano",
            "path": "Instrumentation > Piano",
            "url": "https://ocremix.org/tag/piano"
        },
        {
            "id": "sad",
            "path": "Mood > Sad",
            "url": "https://ocremix.org/tag/sad"
        },
        {
            "id": "solemn",
            "path": "Mood > Solemn",
            "url": "https://ocremix.org/tag/solemn"
        },
        {
            "id": "strings",
            "path": "Instrumentation > Strings",
            "url": "https://ocremix.org/tag/strings"
        },
        {
            "id": "tempo-slow",
            "path": "Time > Tempo: Slow",
            "url": "https://ocremix.org/tag/tempo-slow"
        }
    ],
    "title": "I Had a Name",
    "url": "https://ocremix.org/remix/OCR03101",
    "youtube_url": "https://www.youtube.com/watch?v=-ApNYwM_pmI"
}