{
    "artists": [
        {
            "id": 4607,
            "name": "Binster",
            "url": "https://ocremix.org/artist/4607/binster"
        }
    ],
    "primary_game": "X-Out",
    "tags": [
        {
            "id": "electronic",
            "path": "Instrumentation > Electronic",
            "url": "https://ocremix.org/tag/electronic"
        },
        {
            "id": "synth",
            "path": "Instrumentation > Synth",
            "url": "https://ocremix.org/tag/synth"
        }
    ],
    "title": "LiquidX",
    "url": "https://ocremix.org/remix/OCR01264",
    "youtube_url": "https://www.youtube.com/watch?v=D82ypujAr78"
}