{
    "artists": [
        {
            "id": 14461,
            "name": "Jorito",
            "url": "https://ocremix.org/artist/14461/jorito"
        },
        {
            "id": 17324,
            "name": "Chromatic Apparatus",
            "url": "https://ocremix.org/artist/17324/chromatic-apparatus"
        },
        {
            "id": 18344,
            "name": "Bobbie Jane Desforges",
            "url": "https://ocremix.org/artist/18344/bobbie-jane-desforges"
        }
    ],
    "primary_game": "Octopath Traveler",
    "tags": [
        {
            "id": "cello",
            "path": "Instrumentation > Cello",
            "url": "https://ocremix.org/tag/cello"
        },
        {
            "id": "cinematic",
            "path": "Genre > Cinematic",
            "url": "https://ocremix.org/tag/cinematic"
        },
        {
            "id": "collab",
            "path": "Origin > Collaboration",
            "url": "https://ocremix.org/tag/collab"
        },
        {
            "id": "electronic",
            "path": "Instrumentation > Electronic",
            "url": "https://ocremix.org/tag/electronic"
        },
        {
            "id": "energetic",
            "path": "Mood > Energetic",
            "url": "https://ocremix.org/tag/energetic"
        },
        {
            "id": "epic",
            "path": "Mood > Epic",
            "url": "https://ocremix.org/tag/epic"
        },
        {
            "id": "lyrics-original",
            "path": "Lyrics > Lyrics: Original",
            "url": "https://ocremix.org/tag/lyrics-original"
        },
        {
            "id": "piano",
            "path": "Instrumentation > Piano",
            "url": "https://ocremix.org/tag/piano"
        },
        {
            "id": "saxophone",
            "path": "Instrumentation > Saxophone",
            "url": "https://ocremix.org/tag/saxophone"
        },
        {
            "id": "suspenseful",
            "path": "Mood > Suspenseful",
            "url": "https://ocremix.org/tag/suspenseful"
        },
        {
            "id": "synth",
            "path": "Instrumentation > Synth",
            "url": "https://ocremix.org/tag/synth"
        },
        {
            "id": "synthwave",
            "path": "Genre > EDM > Synthwave",
            "url": "https://ocremix.org/tag/synthwave"
        },
        {
            "id": "vocals-male",
            "path": "Instrumentation > Vocals: Male",
            "url": "https://ocremix.org/tag/vocals-male"
        },
        {
            "id": "vocoder",
            "path": "Effects > Vocoder",
            "url": "https://ocremix.org/tag/vocoder"
        }
    ],
    "title": "At Finis Gate",
    "url": "https://ocremix.org/remix/OCR04359"
}