{
    "artists": [
        {
            "id": 9511,
            "name": "dannyshock",
            "url": "https://ocremix.org/artist/9511/dannyshock"
        }
    ],
    "primary_game": "Contra III: The Alien Wars",
    "tags": [
        {
            "id": "jazz",
            "path": "Genre > Jazz",
            "url": "https://ocremix.org/tag/jazz"
        },
        {
            "id": "organ",
            "path": "Instrumentation > Organ",
            "url": "https://ocremix.org/tag/organ"
        },
        {
            "id": "piano",
            "path": "Instrumentation > Piano",
            "url": "https://ocremix.org/tag/piano"
        },
        {
            "id": "tempo-fast",
            "path": "Time > Tempo: Fast",
            "url": "https://ocremix.org/tag/tempo-fast"
        }
    ],
    "title": "Dystopian Future",
    "url": "https://ocremix.org/remix/OCR02132",
    "youtube_url": "https://www.youtube.com/watch?v=0Kmbiik5gvY"
}