{
    "artists": [
        {
            "id": 14053,
            "name": "JD Harding",
            "url": "https://ocremix.org/artist/14053/jd-harding"
        }
    ],
    "primary_game": "Super Castlevania IV",
    "tags": [
        {
            "id": "dance",
            "path": "Genre > EDM > Dance",
            "url": "https://ocremix.org/tag/dance"
        },
        {
            "id": "electronic",
            "path": "Instrumentation > Electronic",
            "url": "https://ocremix.org/tag/electronic"
        },
        {
            "id": "organ",
            "path": "Instrumentation > Organ",
            "url": "https://ocremix.org/tag/organ"
        },
        {
            "id": "piano",
            "path": "Instrumentation > Piano",
            "url": "https://ocremix.org/tag/piano"
        },
        {
            "id": "timesig-4-4",
            "path": "Time > 4/4 Time Signature",
            "url": "https://ocremix.org/tag/timesig-4-4"
        }
    ],
    "title": "Belmont Mix",
    "url": "https://ocremix.org/remix/OCR01059"
}