{
    "artists": [
        {
            "id": 14461,
            "name": "Jorito",
            "url": "https://ocremix.org/artist/14461/jorito"
        },
        {
            "id": 15473,
            "name": "JohnStacy",
            "url": "https://ocremix.org/artist/15473/johnstacy"
        },
        {
            "id": 15681,
            "name": "JoyDreamer",
            "url": "https://ocremix.org/artist/15681/joydreamer"
        }
    ],
    "primary_game": "Secret of Mana",
    "title": "Whispers",
    "url": "https://ocremix.org/remix/OCR03652"
}