{
    "artists": [
        {
            "id": 4285,
            "name": "Disco Dan",
            "url": "https://ocremix.org/artist/4285/disco-dan"
        }
    ],
    "primary_game": "Mega Man 3",
    "tags": [
        {
            "id": "electronic",
            "path": "Instrumentation > Electronic",
            "url": "https://ocremix.org/tag/electronic"
        },
        {
            "id": "happy",
            "path": "Mood > Happy",
            "url": "https://ocremix.org/tag/happy"
        },
        {
            "id": "house",
            "path": "Genre > EDM > House",
            "url": "https://ocremix.org/tag/house"
        },
        {
            "id": "piano",
            "path": "Instrumentation > Piano",
            "url": "https://ocremix.org/tag/piano"
        },
        {
            "id": "sitar",
            "path": "Instrumentation > Sitar",
            "url": "https://ocremix.org/tag/sitar"
        },
        {
            "id": "synth",
            "path": "Instrumentation > Synth",
            "url": "https://ocremix.org/tag/synth"
        },
        {
            "id": "tempo-fast",
            "path": "Time > Tempo: Fast",
            "url": "https://ocremix.org/tag/tempo-fast"
        },
        {
            "id": "timesig-4-4",
            "path": "Time > 4/4 Time Signature",
            "url": "https://ocremix.org/tag/timesig-4-4"
        },
        {
            "id": "trance",
            "path": "Genre > EDM > Trance",
            "url": "https://ocremix.org/tag/trance"
        },
        {
            "id": "violin",
            "path": "Instrumentation > Violin",
            "url": "https://ocremix.org/tag/violin"
        },
        {
            "id": "workout",
            "path": "Usage > Workout",
            "url": "https://ocremix.org/tag/workout"
        }
    ],
    "title": "Get Down",
    "url": "https://ocremix.org/remix/OCR00397"
}