{
    "artists": [
        {
            "id": 13668,
            "name": "Bluelighter",
            "url": "https://ocremix.org/artist/13668/bluelighter"
        }
    ],
    "primary_game": "Final Fantasy VIII",
    "tags": [
        {
            "id": "classical",
            "path": "Genre > Classical",
            "url": "https://ocremix.org/tag/classical"
        },
        {
            "id": "jazz",
            "path": "Genre > Jazz",
            "url": "https://ocremix.org/tag/jazz"
        },
        {
            "id": "piano",
            "path": "Instrumentation > Piano",
            "url": "https://ocremix.org/tag/piano"
        },
        {
            "id": "solo",
            "path": "Arrangement > Solo",
            "url": "https://ocremix.org/tag/solo"
        },
        {
            "id": "solo-piano",
            "path": "Instrumentation > Solo Piano",
            "url": "https://ocremix.org/tag/solo-piano"
        },
        {
            "id": "suspenseful",
            "path": "Mood > Suspenseful",
            "url": "https://ocremix.org/tag/suspenseful"
        }
    ],
    "title": "Selphie's Operation",
    "url": "https://ocremix.org/remix/OCR04160",
    "youtube_url": "https://www.youtube.com/watch?v=noHArlg-e3E"
}