{
    "artists": [
        {
            "id": 13047,
            "name": "Melodious Punk",
            "url": "https://ocremix.org/artist/13047/melodious-punk"
        }
    ],
    "primary_game": "Secret of Mana",
    "tags": [
        {
            "id": "acoustic-guitar",
            "path": "Instrumentation > Acoustic Guitar",
            "url": "https://ocremix.org/tag/acoustic-guitar"
        },
        {
            "id": "ambient",
            "path": "Genre > Easy Listening > Ambient",
            "url": "https://ocremix.org/tag/ambient"
        },
        {
            "id": "electric-guitar",
            "path": "Instrumentation > Electric Guitar",
            "url": "https://ocremix.org/tag/electric-guitar"
        },
        {
            "id": "jazz",
            "path": "Genre > Jazz",
            "url": "https://ocremix.org/tag/jazz"
        },
        {
            "id": "mellow",
            "path": "Mood > Mellow",
            "url": "https://ocremix.org/tag/mellow"
        }
    ],
    "title": "Curious",
    "url": "https://ocremix.org/remix/OCR02714",
    "youtube_url": "https://www.youtube.com/watch?v=HPVhxZpqGiY"
}