{
    "artists": [
        {
            "id": 12783,
            "name": "Jamphibious",
            "url": "https://ocremix.org/artist/12783/jamphibious"
        }
    ],
    "primary_game": "Pok\u00e9mon X",
    "tags": [
        {
            "id": "aggressive",
            "path": "Mood > Aggressive",
            "url": "https://ocremix.org/tag/aggressive"
        },
        {
            "id": "edm",
            "path": "Genre > EDM",
            "url": "https://ocremix.org/tag/edm"
        },
        {
            "id": "electric-guitar",
            "path": "Instrumentation > Electric Guitar",
            "url": "https://ocremix.org/tag/electric-guitar"
        },
        {
            "id": "electric-piano",
            "path": "Instrumentation > Electric Piano",
            "url": "https://ocremix.org/tag/electric-piano"
        },
        {
            "id": "rock",
            "path": "Genre > Rock",
            "url": "https://ocremix.org/tag/rock"
        },
        {
            "id": "synth",
            "path": "Instrumentation > Synth",
            "url": "https://ocremix.org/tag/synth"
        }
    ],
    "title": "Forest Fire",
    "url": "https://ocremix.org/remix/OCR03076",
    "youtube_url": "https://www.youtube.com/watch?v=Ug9bNYjiBTI"
}