{
    "artists": [
        {
            "id": 4729,
            "name": "OceansAndrew",
            "url": "https://ocremix.org/artist/4729/oceansandrew"
        },
        {
            "id": 4765,
            "name": "Scaredsim",
            "url": "https://ocremix.org/artist/4765/scaredsim"
        }
    ],
    "primary_game": "Gradius III",
    "tags": [
        {
            "id": "collab",
            "path": "Origin > Collaboration",
            "url": "https://ocremix.org/tag/collab"
        },
        {
            "id": "electric-guitar",
            "path": "Instrumentation > Electric Guitar",
            "url": "https://ocremix.org/tag/electric-guitar"
        },
        {
            "id": "rock",
            "path": "Genre > Rock",
            "url": "https://ocremix.org/tag/rock"
        },
        {
            "id": "synth",
            "path": "Instrumentation > Synth",
            "url": "https://ocremix.org/tag/synth"
        }
    ],
    "title": "Declaration of War",
    "url": "https://ocremix.org/remix/OCR01830",
    "youtube_url": "https://www.youtube.com/watch?v=wsHIMJ5sXq8"
}