{
    "artists": [
        {
            "id": 4751,
            "name": "Mattias H\u00e4ggstr\u00f6m Gerdt",
            "url": "https://ocremix.org/artist/4751/mattias-haggstrom-gerdt"
        }
    ],
    "primary_game": "Final Fantasy VI",
    "tags": [
        {
            "id": "electronic",
            "path": "Instrumentation > Electronic",
            "url": "https://ocremix.org/tag/electronic"
        },
        {
            "id": "industrial",
            "path": "Genre > EDM > Industrial",
            "url": "https://ocremix.org/tag/industrial"
        },
        {
            "id": "synth",
            "path": "Instrumentation > Synth",
            "url": "https://ocremix.org/tag/synth"
        }
    ],
    "title": "Magicite Made My Mind Melt",
    "url": "https://ocremix.org/remix/OCR01868",
    "youtube_url": "https://www.youtube.com/watch?v=JWoLYBGx4D4"
}