{
    "artists": [
        {
            "id": 4279,
            "name": "djpretzel",
            "url": "https://ocremix.org/artist/4279/djpretzel"
        }
    ],
    "primary_game": "Lunar: The Silver Star",
    "tags": [
        {
            "id": "distortion",
            "path": "Effects > Distortion",
            "url": "https://ocremix.org/tag/distortion"
        },
        {
            "id": "duration-short",
            "path": "Time > Duration: Short",
            "url": "https://ocremix.org/tag/duration-short"
        },
        {
            "id": "electro",
            "path": "Genre > EDM > Electro",
            "url": "https://ocremix.org/tag/electro"
        },
        {
            "id": "lo-fi",
            "path": "Effects > Lo-Fi",
            "url": "https://ocremix.org/tag/lo-fi"
        },
        {
            "id": "lyrics-existing",
            "path": "Lyrics > Lyrics: Existing",
            "url": "https://ocremix.org/tag/lyrics-existing"
        },
        {
            "id": "pop",
            "path": "Genre > Pop",
            "url": "https://ocremix.org/tag/pop"
        },
        {
            "id": "quirky",
            "path": "Mood > Quirky",
            "url": "https://ocremix.org/tag/quirky"
        },
        {
            "id": "singing",
            "path": "Instrumentation > Singing",
            "url": "https://ocremix.org/tag/singing"
        },
        {
            "id": "synth",
            "path": "Instrumentation > Synth",
            "url": "https://ocremix.org/tag/synth"
        },
        {
            "id": "tempo-moderate",
            "path": "Time > Tempo: Moderate",
            "url": "https://ocremix.org/tag/tempo-moderate"
        },
        {
            "id": "vocals-male",
            "path": "Instrumentation > Vocals: Male",
            "url": "https://ocremix.org/tag/vocals-male"
        }
    ],
    "title": "Singing Pretzel",
    "url": "https://ocremix.org/remix/OCR00214",
    "youtube_url": "https://www.youtube.com/watch?v=sxi5rTPihf8"
}