{
    "artists": [
        {
            "id": 4685,
            "name": "Juan Medrano",
            "url": "https://ocremix.org/artist/4685/juan-medrano"
        }
    ],
    "primary_game": "Mega Man X8",
    "tags": [
        {
            "id": "aggressive",
            "path": "Mood > Aggressive",
            "url": "https://ocremix.org/tag/aggressive"
        },
        {
            "id": "electric-guitar",
            "path": "Instrumentation > Electric Guitar",
            "url": "https://ocremix.org/tag/electric-guitar"
        },
        {
            "id": "metal",
            "path": "Genre > Rock > Metal",
            "url": "https://ocremix.org/tag/metal"
        },
        {
            "id": "organ",
            "path": "Instrumentation > Organ",
            "url": "https://ocremix.org/tag/organ"
        },
        {
            "id": "rock",
            "path": "Genre > Rock",
            "url": "https://ocremix.org/tag/rock"
        },
        {
            "id": "tempo-fast",
            "path": "Time > Tempo: Fast",
            "url": "https://ocremix.org/tag/tempo-fast"
        }
    ],
    "title": "Winged Reploid (Revelation)",
    "url": "https://ocremix.org/remix/OCR02402"
}