{
    "artists": [
        {
            "id": 4701,
            "name": "Adrian Holovaty",
            "url": "https://ocremix.org/artist/4701/adrian-holovaty"
        }
    ],
    "primary_game": "Super Mario Bros. 2",
    "tags": [
        {
            "id": "acoustic-guitar",
            "path": "Instrumentation > Acoustic Guitar",
            "url": "https://ocremix.org/tag/acoustic-guitar"
        },
        {
            "id": "duration-short",
            "path": "Time > Duration: Short",
            "url": "https://ocremix.org/tag/duration-short"
        },
        {
            "id": "jazz",
            "path": "Genre > Jazz",
            "url": "https://ocremix.org/tag/jazz"
        },
        {
            "id": "jazzy",
            "path": "Mood > Jazzy",
            "url": "https://ocremix.org/tag/jazzy"
        },
        {
            "id": "live-recording",
            "path": "Production > Live Recording",
            "url": "https://ocremix.org/tag/live-recording"
        },
        {
            "id": "solo",
            "path": "Arrangement > Solo",
            "url": "https://ocremix.org/tag/solo"
        }
    ],
    "title": "Gypsy Jazz",
    "url": "https://ocremix.org/remix/OCR01466",
    "youtube_url": "https://www.youtube.com/watch?v=_rnQbq8SLK4"
}