{
    "artists": [
        {
            "id": 10670,
            "name": "Doc Nano",
            "url": "https://ocremix.org/artist/10670/doc-nano"
        },
        {
            "id": 10896,
            "name": "Evory",
            "url": "https://ocremix.org/artist/10896/evory"
        }
    ],
    "primary_game": "DuckTales",
    "tags": [
        {
            "id": "collab",
            "path": "Origin > Collaboration",
            "url": "https://ocremix.org/tag/collab"
        },
        {
            "id": "mellow",
            "path": "Mood > Mellow",
            "url": "https://ocremix.org/tag/mellow"
        },
        {
            "id": "piano",
            "path": "Instrumentation > Piano",
            "url": "https://ocremix.org/tag/piano"
        },
        {
            "id": "romantic",
            "path": "Mood > Romantic",
            "url": "https://ocremix.org/tag/romantic"
        },
        {
            "id": "solo",
            "path": "Arrangement > Solo",
            "url": "https://ocremix.org/tag/solo"
        },
        {
            "id": "solo-piano",
            "path": "Instrumentation > Solo Piano",
            "url": "https://ocremix.org/tag/solo-piano"
        }
    ],
    "title": "Ebbed Tides and Webbed Feet",
    "url": "https://ocremix.org/remix/OCR02360"
}