{
    "artists": [
        {
            "id": 4529,
            "name": "ella guro",
            "url": "https://ocremix.org/artist/4529/ella-guro"
        }
    ],
    "primary_game": "Super Mario World",
    "tags": [
        {
            "id": "dark",
            "path": "Mood > Dark",
            "url": "https://ocremix.org/tag/dark"
        },
        {
            "id": "electric-piano",
            "path": "Instrumentation > Electric Piano",
            "url": "https://ocremix.org/tag/electric-piano"
        },
        {
            "id": "halloween",
            "path": "Usage > Halloween",
            "url": "https://ocremix.org/tag/halloween"
        },
        {
            "id": "spooky",
            "path": "Mood > Spooky",
            "url": "https://ocremix.org/tag/spooky"
        }
    ],
    "title": "Da Phunky Forest",
    "url": "https://ocremix.org/remix/OCR00908"
}