{
    "artists": [
        {
            "id": 4761,
            "name": "Cerrax",
            "url": "https://ocremix.org/artist/4761/cerrax"
        }
    ],
    "primary_game": "Pok\u00e9mon Red Version",
    "tags": [
        {
            "id": "ambient",
            "path": "Genre > Easy Listening > Ambient",
            "url": "https://ocremix.org/tag/ambient"
        },
        {
            "id": "dark",
            "path": "Mood > Dark",
            "url": "https://ocremix.org/tag/dark"
        },
        {
            "id": "electronic",
            "path": "Instrumentation > Electronic",
            "url": "https://ocremix.org/tag/electronic"
        },
        {
            "id": "industrial",
            "path": "Genre > EDM > Industrial",
            "url": "https://ocremix.org/tag/industrial"
        },
        {
            "id": "synth",
            "path": "Instrumentation > Synth",
            "url": "https://ocremix.org/tag/synth"
        }
    ],
    "title": "Out of Antidote",
    "url": "https://ocremix.org/remix/OCR02197"
}