{
    "artists": [
        {
            "id": 5178,
            "name": "PROTO\u00b7DOME",
            "url": "https://ocremix.org/artist/5178/protodome"
        }
    ],
    "primary_game": "Scribblenauts",
    "tags": [
        {
            "id": "chiptune",
            "path": "Instrumentation > Chiptune",
            "url": "https://ocremix.org/tag/chiptune"
        },
        {
            "id": "electronic",
            "path": "Instrumentation > Electronic",
            "url": "https://ocremix.org/tag/electronic"
        },
        {
            "id": "happy",
            "path": "Mood > Happy",
            "url": "https://ocremix.org/tag/happy"
        },
        {
            "id": "synth",
            "path": "Instrumentation > Synth",
            "url": "https://ocremix.org/tag/synth"
        }
    ],
    "title": "NO (resub)",
    "url": "https://ocremix.org/remix/OCR02083",
    "youtube_url": "https://www.youtube.com/watch?v=rZelHlm8e-A"
}