{
    "artists": [
        {
            "id": 5628,
            "name": "AMT",
            "url": "https://ocremix.org/artist/5628/amt"
        }
    ],
    "primary_game": "Donkey Kong Country 2: Diddy's Kong Quest",
    "tags": [
        {
            "id": "electric-guitar",
            "path": "Instrumentation > Electric Guitar",
            "url": "https://ocremix.org/tag/electric-guitar"
        },
        {
            "id": "rock",
            "path": "Genre > Rock",
            "url": "https://ocremix.org/tag/rock"
        }
    ],
    "title": "Can't Stop the Hot-Head Bop",
    "url": "https://ocremix.org/remix/OCR02146",
    "youtube_url": "https://www.youtube.com/watch?v=ugE9KAPrFZ8"
}