{
    "artists": [
        {
            "id": 4324,
            "name": "FFmusic Dj",
            "url": "https://ocremix.org/artist/4324/ffmusic-dj"
        }
    ],
    "primary_game": "Final Fantasy IV",
    "tags": [
        {
            "id": "happy",
            "path": "Mood > Happy",
            "url": "https://ocremix.org/tag/happy"
        },
        {
            "id": "house",
            "path": "Genre > EDM > House",
            "url": "https://ocremix.org/tag/house"
        },
        {
            "id": "synth",
            "path": "Instrumentation > Synth",
            "url": "https://ocremix.org/tag/synth"
        },
        {
            "id": "tempo-moderate",
            "path": "Time > Tempo: Moderate",
            "url": "https://ocremix.org/tag/tempo-moderate"
        },
        {
            "id": "timesig-4-4",
            "path": "Time > 4/4 Time Signature",
            "url": "https://ocremix.org/tag/timesig-4-4"
        },
        {
            "id": "trance",
            "path": "Genre > EDM > Trance",
            "url": "https://ocremix.org/tag/trance"
        }
    ],
    "title": "Ground Up",
    "url": "https://ocremix.org/remix/OCR00436"
}