{
    "artists": [
        {
            "id": 11960,
            "name": "fredrikd",
            "url": "https://ocremix.org/artist/11960/fredrikd"
        }
    ],
    "primary_game": "Mega Man",
    "tags": [
        {
            "id": "acoustic-guitar",
            "path": "Instrumentation > Acoustic Guitar",
            "url": "https://ocremix.org/tag/acoustic-guitar"
        },
        {
            "id": "compo",
            "path": "Origin > Competition",
            "url": "https://ocremix.org/tag/compo"
        },
        {
            "id": "electric-guitar",
            "path": "Instrumentation > Electric Guitar",
            "url": "https://ocremix.org/tag/electric-guitar"
        },
        {
            "id": "mellow",
            "path": "Mood > Mellow",
            "url": "https://ocremix.org/tag/mellow"
        },
        {
            "id": "rock",
            "path": "Genre > Rock",
            "url": "https://ocremix.org/tag/rock"
        },
        {
            "id": "strings",
            "path": "Instrumentation > Strings",
            "url": "https://ocremix.org/tag/strings"
        }
    ],
    "title": "Wonderful Shadows by the Electric Sheep Orchestra (stereo)",
    "url": "https://ocremix.org/remix/OCR02441"
}