{
    "artists": [
        {
            "id": 4304,
            "name": "Mustin",
            "url": "https://ocremix.org/artist/4304/mustin"
        },
        {
            "id": 4425,
            "name": "Kassi",
            "url": "https://ocremix.org/artist/4425/kassi"
        }
    ],
    "primary_game": "Secret of Mana",
    "tags": [
        {
            "id": "ambient",
            "path": "Genre > Easy Listening > Ambient",
            "url": "https://ocremix.org/tag/ambient"
        },
        {
            "id": "ballad",
            "path": "Genre > Easy Listening > Ballad",
            "url": "https://ocremix.org/tag/ballad"
        },
        {
            "id": "cello",
            "path": "Instrumentation > Cello",
            "url": "https://ocremix.org/tag/cello"
        },
        {
            "id": "collab",
            "path": "Origin > Collaboration",
            "url": "https://ocremix.org/tag/collab"
        },
        {
            "id": "duration-short",
            "path": "Time > Duration: Short",
            "url": "https://ocremix.org/tag/duration-short"
        },
        {
            "id": "electric-piano",
            "path": "Instrumentation > Electric Piano",
            "url": "https://ocremix.org/tag/electric-piano"
        },
        {
            "id": "flute",
            "path": "Instrumentation > Flute",
            "url": "https://ocremix.org/tag/flute"
        },
        {
            "id": "live-instruments",
            "path": "Production > Live Instruments",
            "url": "https://ocremix.org/tag/live-instruments"
        },
        {
            "id": "meditation",
            "path": "Usage > Meditation",
            "url": "https://ocremix.org/tag/meditation"
        },
        {
            "id": "orchestral",
            "path": "Instrumentation > Orchestral",
            "url": "https://ocremix.org/tag/orchestral"
        },
        {
            "id": "peaceful",
            "path": "Mood > Peaceful",
            "url": "https://ocremix.org/tag/peaceful"
        },
        {
            "id": "piano",
            "path": "Instrumentation > Piano",
            "url": "https://ocremix.org/tag/piano"
        },
        {
            "id": "sad",
            "path": "Mood > Sad",
            "url": "https://ocremix.org/tag/sad"
        },
        {
            "id": "solemn",
            "path": "Mood > Solemn",
            "url": "https://ocremix.org/tag/solemn"
        },
        {
            "id": "strings",
            "path": "Instrumentation > Strings",
            "url": "https://ocremix.org/tag/strings"
        },
        {
            "id": "tempo-slow",
            "path": "Time > Tempo: Slow",
            "url": "https://ocremix.org/tag/tempo-slow"
        },
        {
            "id": "timesig-4-4",
            "path": "Time > 4/4 Time Signature",
            "url": "https://ocremix.org/tag/timesig-4-4"
        }
    ],
    "title": "Cry from the Forest",
    "url": "https://ocremix.org/remix/OCR00444",
    "youtube_url": "https://www.youtube.com/watch?v=I3t9sWnwIKk"
}