{
    "artists": [
        {
            "id": 16118,
            "name": "Sagnewshreds",
            "url": "https://ocremix.org/artist/16118/sagnewshreds"
        },
        {
            "id": 16431,
            "name": "Brian Westbrook",
            "url": "https://ocremix.org/artist/16431/brian-westbrook"
        },
        {
            "id": 16432,
            "name": "Mike Dreher",
            "url": "https://ocremix.org/artist/16432/mike-dreher"
        },
        {
            "id": 16433,
            "name": "Tony Barhoum",
            "url": "https://ocremix.org/artist/16433/tony-barhoum"
        }
    ],
    "primary_game": "Final Fantasy VI",
    "tags": [
        {
            "id": "aggressive",
            "path": "Mood > Aggressive",
            "url": "https://ocremix.org/tag/aggressive"
        },
        {
            "id": "collab",
            "path": "Origin > Collaboration",
            "url": "https://ocremix.org/tag/collab"
        },
        {
            "id": "compo-dod",
            "path": "Origin > Competition > Dwelling of Duels",
            "url": "https://ocremix.org/tag/compo-dod"
        },
        {
            "id": "dark",
            "path": "Mood > Dark",
            "url": "https://ocremix.org/tag/dark"
        },
        {
            "id": "distortion",
            "path": "Effects > Distortion",
            "url": "https://ocremix.org/tag/distortion"
        },
        {
            "id": "electric-guitar",
            "path": "Instrumentation > Electric Guitar",
            "url": "https://ocremix.org/tag/electric-guitar"
        },
        {
            "id": "energetic",
            "path": "Mood > Energetic",
            "url": "https://ocremix.org/tag/energetic"
        },
        {
            "id": "epic",
            "path": "Mood > Epic",
            "url": "https://ocremix.org/tag/epic"
        },
        {
            "id": "extended-soloing",
            "path": "Arrangement > Extended Soloing",
            "url": "https://ocremix.org/tag/extended-soloing"
        },
        {
            "id": "metal",
            "path": "Genre > Rock > Metal",
            "url": "https://ocremix.org/tag/metal"
        },
        {
            "id": "punk",
            "path": "Genre > Rock > Punk",
            "url": "https://ocremix.org/tag/punk"
        },
        {
            "id": "tempo-fast",
            "path": "Time > Tempo: Fast",
            "url": "https://ocremix.org/tag/tempo-fast"
        }
    ],
    "title": "Six Feet Beneath the Veldt",
    "url": "https://ocremix.org/remix/OCR03795",
    "youtube_url": "https://www.youtube.com/watch?v=_MxbUmQy5w8"
}