{
    "artists": [
        {
            "id": 13080,
            "name": "ectogemia",
            "url": "https://ocremix.org/artist/13080/ectogemia"
        }
    ],
    "primary_game": "Pok\u00e9mon Gold Version",
    "tags": [
        {
            "id": "ambient",
            "path": "Genre > Easy Listening > Ambient",
            "url": "https://ocremix.org/tag/ambient"
        },
        {
            "id": "electronic",
            "path": "Instrumentation > Electronic",
            "url": "https://ocremix.org/tag/electronic"
        },
        {
            "id": "funk",
            "path": "Genre > R&B > Funk",
            "url": "https://ocremix.org/tag/funk"
        },
        {
            "id": "jazz",
            "path": "Genre > Jazz",
            "url": "https://ocremix.org/tag/jazz"
        },
        {
            "id": "piano",
            "path": "Instrumentation > Piano",
            "url": "https://ocremix.org/tag/piano"
        },
        {
            "id": "synth",
            "path": "Instrumentation > Synth",
            "url": "https://ocremix.org/tag/synth"
        }
    ],
    "title": "Half Steps",
    "url": "https://ocremix.org/remix/OCR02728",
    "youtube_url": "https://www.youtube.com/watch?v=SZp0vSMT52Q"
}