{
    "artists": [
        {
            "id": 13147,
            "name": "timaeus222",
            "url": "https://ocremix.org/artist/13147/timaeus222"
        }
    ],
    "primary_game": "Fittest",
    "tags": [
        {
            "id": "cowbell",
            "path": "Instrumentation > Cowbell",
            "url": "https://ocremix.org/tag/cowbell"
        },
        {
            "id": "electric-piano",
            "path": "Instrumentation > Electric Piano",
            "url": "https://ocremix.org/tag/electric-piano"
        },
        {
            "id": "funky",
            "path": "Mood > Funky",
            "url": "https://ocremix.org/tag/funky"
        },
        {
            "id": "fusion",
            "path": "Genre > Jazz > Fusion",
            "url": "https://ocremix.org/tag/fusion"
        },
        {
            "id": "jazzy",
            "path": "Mood > Jazzy",
            "url": "https://ocremix.org/tag/jazzy"
        },
        {
            "id": "medley",
            "path": "Arrangement > Medley",
            "url": "https://ocremix.org/tag/medley"
        },
        {
            "id": "piano",
            "path": "Instrumentation > Piano",
            "url": "https://ocremix.org/tag/piano"
        },
        {
            "id": "synth",
            "path": "Instrumentation > Synth",
            "url": "https://ocremix.org/tag/synth"
        }
    ],
    "title": "Contrapuntal Field",
    "url": "https://ocremix.org/remix/OCR03225",
    "youtube_url": "https://www.youtube.com/watch?v=QrwWbZX1igs"
}