{
    "artists": [
        {
            "id": 4651,
            "name": "Ben Briggs",
            "url": "https://ocremix.org/artist/4651/ben-briggs"
        },
        {
            "id": 11939,
            "name": "Pete Lepley",
            "url": "https://ocremix.org/artist/11939/pete-lepley"
        }
    ],
    "primary_game": "Sonic the Hedgehog 2",
    "tags": [
        {
            "id": "chiptune",
            "path": "Instrumentation > Chiptune",
            "url": "https://ocremix.org/tag/chiptune"
        },
        {
            "id": "collab",
            "path": "Origin > Collaboration",
            "url": "https://ocremix.org/tag/collab"
        },
        {
            "id": "extended-soloing",
            "path": "Arrangement > Extended Soloing",
            "url": "https://ocremix.org/tag/extended-soloing"
        },
        {
            "id": "funk",
            "path": "Genre > R&B > Funk",
            "url": "https://ocremix.org/tag/funk"
        },
        {
            "id": "funky",
            "path": "Mood > Funky",
            "url": "https://ocremix.org/tag/funky"
        },
        {
            "id": "synth",
            "path": "Instrumentation > Synth",
            "url": "https://ocremix.org/tag/synth"
        },
        {
            "id": "timesig-4-4",
            "path": "Time > 4/4 Time Signature",
            "url": "https://ocremix.org/tag/timesig-4-4"
        }
    ],
    "title": "Ruinous Ruins!",
    "url": "https://ocremix.org/remix/OCR03196",
    "youtube_url": "https://www.youtube.com/watch?v=b2ZKie8UiJo"
}