{
    "artists": [
        {
            "id": 4758,
            "name": "Beckett007",
            "url": "https://ocremix.org/artist/4758/beckett007"
        }
    ],
    "primary_game": "Wolfenstein 3D",
    "tags": [
        {
            "id": "brass",
            "path": "Instrumentation > Brass",
            "url": "https://ocremix.org/tag/brass"
        },
        {
            "id": "cinematic",
            "path": "Genre > Cinematic",
            "url": "https://ocremix.org/tag/cinematic"
        },
        {
            "id": "orchestral",
            "path": "Instrumentation > Orchestral",
            "url": "https://ocremix.org/tag/orchestral"
        },
        {
            "id": "strings",
            "path": "Instrumentation > Strings",
            "url": "https://ocremix.org/tag/strings"
        }
    ],
    "title": "Blazkowicz's Great Escape",
    "url": "https://ocremix.org/remix/OCR02020",
    "youtube_url": "https://www.youtube.com/watch?v=qYq-mXNDNHM"
}